container_runtime_interface_api-2.0.1.dist-info/licenses/LICENSE
cri_api/__init__.py
cri_api/channel.py
cri_api/containers.py
cri_api/exceptions.py
cri_api/images.py
cri_api/py.typed
cri_api/github/com/gogo/protobuf/gogoproto/__init__.py
cri_api/github/com/gogo/protobuf/gogoproto/gogo_pb2.py
cri_api/github/com/gogo/protobuf/gogoproto/gogo_pb2.pyi
cri_api/github/com/gogo/protobuf/gogoproto/gogo_pb2_grpc.py
cri_api/v1/api_pb2.py
cri_api/v1/api_pb2.pyi
cri_api/v1/api_pb2_grpc.py
cri_api/v1alpha2/api_pb2.py
cri_api/v1alpha2/api_pb2.pyi
cri_api/v1alpha2/api_pb2_grpc.py
container_runtime_interface_api-2.0.1.dist-info/METADATA
container_runtime_interface_api-2.0.1.dist-info/WHEEL
container_runtime_interface_api-2.0.1.dist-info/top_level.txt
container_runtime_interface_api-2.0.1.dist-info/RECORD
