Metadata-Version: 2.4
Name: container-runtime-interface-api
Version: 2.0.1
Summary: Python library for interaction with the Kubernetes container runtime interface API.
Home-page: https://github.com/dominodatalab/container-runtime-interface-api
Author: Domino Data Lab
Author-email: steven.davidovitz@dominodatalab.com
Classifier: Programming Language :: Python :: 3
Classifier: License :: OSI Approved :: Apache Software License
Classifier: Operating System :: OS Independent
Requires-Python: >=3.10
License-File: LICENSE
Requires-Dist: grpcio~=1.73
Requires-Dist: protobuf~=6.31
Dynamic: author
Dynamic: author-email
Dynamic: classifier
Dynamic: description
Dynamic: description-content-type
Dynamic: home-page
Dynamic: license-file
Dynamic: requires-dist
Dynamic: requires-python
Dynamic: summary
